setup.py
rHDPE_Data_Analysis/Deprecated.py
rHDPE_Data_Analysis/Global_Utilities.py
rHDPE_Data_Analysis/__init__.py
rHDPE_Data_Analysis.egg-info/PKG-INFO
rHDPE_Data_Analysis.egg-info/SOURCES.txt
rHDPE_Data_Analysis.egg-info/dependency_links.txt
rHDPE_Data_Analysis.egg-info/top_level.txt
rHDPE_Data_Analysis/Colour_Analysis/Analysis.py
rHDPE_Data_Analysis/Colour_Analysis/Colour_plotting.py
rHDPE_Data_Analysis/Colour_Analysis/Input_Parameters_Class.py
rHDPE_Data_Analysis/Colour_Analysis/Preprocessing.py
rHDPE_Data_Analysis/Colour_Analysis/Utilities.py
rHDPE_Data_Analysis/Colour_Analysis/__init__.py
rHDPE_Data_Analysis/DSC_Analysis/Analysis.py
rHDPE_Data_Analysis/DSC_Analysis/DSC_plotting.py
rHDPE_Data_Analysis/DSC_Analysis/Deprecated.py
rHDPE_Data_Analysis/DSC_Analysis/Input_Parameters_Class.py
rHDPE_Data_Analysis/DSC_Analysis/Preprocessing.py
rHDPE_Data_Analysis/DSC_Analysis/Utilities.py
rHDPE_Data_Analysis/DSC_Analysis/__init__.py
rHDPE_Data_Analysis/ESCR_Analysis/Analysis.py
rHDPE_Data_Analysis/ESCR_Analysis/ESCR_plotting.py
rHDPE_Data_Analysis/ESCR_Analysis/Input_Parameters_Class.py
rHDPE_Data_Analysis/ESCR_Analysis/Preprocessing.py
rHDPE_Data_Analysis/ESCR_Analysis/Utilities.py
rHDPE_Data_Analysis/ESCR_Analysis/__init__.py
rHDPE_Data_Analysis/FTIR_Analysis/Analysis.py
rHDPE_Data_Analysis/FTIR_Analysis/Deprecated.py
rHDPE_Data_Analysis/FTIR_Analysis/FTIR_plotting.py
rHDPE_Data_Analysis/FTIR_Analysis/Input_Parameters_Class.py
rHDPE_Data_Analysis/FTIR_Analysis/Preprocessing.py
rHDPE_Data_Analysis/FTIR_Analysis/Utilities.py
rHDPE_Data_Analysis/FTIR_Analysis/__init__.py
rHDPE_Data_Analysis/GCMS_Analysis/Analysis.py
rHDPE_Data_Analysis/GCMS_Analysis/GCMS_plotting.py
rHDPE_Data_Analysis/GCMS_Analysis/Input_Parameters_Class.py
rHDPE_Data_Analysis/GCMS_Analysis/Preprocessing.py
rHDPE_Data_Analysis/GCMS_Analysis/Utilities.py
rHDPE_Data_Analysis/GCMS_Analysis/__init__.py
rHDPE_Data_Analysis/GPC_Analysis/Analysis.py
rHDPE_Data_Analysis/GPC_Analysis/GPC_plotting.py
rHDPE_Data_Analysis/GPC_Analysis/Input_Parameters_Class.py
rHDPE_Data_Analysis/GPC_Analysis/Preprocessing.py
rHDPE_Data_Analysis/GPC_Analysis/Utilities.py
