Metadata-Version: 2.1
Name: rHDPE-Data-Analysis
Version: 1.0.150
Summary: Package for analysing data relating to recycled HDPE
Author: Phil Smith
Author-email: pvsmith100@btinternet.com
Classifier: Programming Language :: Python :: 3
Classifier: License :: OSI Approved :: MIT License
Classifier: Operating System :: OS Independent
Requires-Python: >=3.6
